conductor/__init__.py
conductor/client/__init__.py
conductor/client/automator/__init__.py
conductor/client/automator/task_handler.py
conductor/client/automator/task_runner.py
conductor/client/automator/utils.py
conductor/client/configuration/__init__.py
conductor/client/configuration/configuration.py
conductor/client/configuration/settings/__init__.py
conductor/client/configuration/settings/authentication_settings.py
conductor/client/exceptions/__init__.py
conductor/client/exceptions/api_error.py
conductor/client/exceptions/api_exception_handler.py
conductor/client/helpers/__init__.py
conductor/client/helpers/helper.py
conductor/client/http/__init__.py
conductor/client/http/api_client.py
conductor/client/http/rest.py
conductor/client/http/thread.py
conductor/client/http/api/__init__.py
conductor/client/http/api/metadata_resource_api.py
conductor/client/http/api/task_resource_api.py
conductor/client/http/models/__init__.py
conductor/client/http/models/action.py
conductor/client/http/models/auditable.py
conductor/client/http/models/authorization_request.py
conductor/client/http/models/bulk_response.py
conductor/client/http/models/conductor_application.py
conductor/client/http/models/conductor_user.py
conductor/client/http/models/correlation_ids_search_request.py
conductor/client/http/models/create_or_update_application_request.py
conductor/client/http/models/event_handler.py
conductor/client/http/models/external_storage_location.py
conductor/client/http/models/generate_token_request.py
conductor/client/http/models/group.py
conductor/client/http/models/health.py
conductor/client/http/models/health_check_status.py
conductor/client/http/models/integration.py
conductor/client/http/models/integration_api.py
conductor/client/http/models/integration_api_update.py
conductor/client/http/models/integration_def.py
conductor/client/http/models/integration_update.py
conductor/client/http/models/permission.py
conductor/client/http/models/poll_data.py
user_agent_sdk-0.3.0.dist-info/METADATA
user_agent_sdk-0.3.0.dist-info/WHEEL
user_agent_sdk-0.3.0.dist-info/entry_points.txt
user_agent_sdk-0.3.0.dist-info/licenses/LICENSE
user_agent_sdk-0.3.0.dist-info/RECORD
