Metadata-Version: 2.4
Name: user-agent-sdk
Version: 0.3.0
Summary: A secure SDK for building custom user agents (workers) that run in your environment and connect safely with the akaBot 2.0 platform.
Project-URL: Homepage, https://nextdev.akabot.io
Author: akaBot Team
License-Expression: Apache-2.0
License-File: LICENSE
Keywords: RPA,akaBot,automation,sdk,user-agent,worker
Classifier: Intended Audience :: Developers
Classifier: License :: OSI Approved :: Apache Software License
Classifier: Programming Language :: Python :: 3.12
Classifier: Programming Language :: Python :: 3.13
Classifier: Topic :: Software Development :: Libraries
Classifier: Typing :: Typed
Requires-Python: >=3.12
Requires-Dist: cyclopts>=4.2.1
Requires-Dist: dacite>=1.8.1
Requires-Dist: deprecated>=1.3.1
Requires-Dist: httpx>=0.28.1
Requires-Dist: pillow>=12.0.0
Requires-Dist: requests>=2.32.5
Requires-Dist: six>=1.17.0
Requires-Dist: typing-extensions>=4.15.0
Requires-Dist: websockets>=15.0.1
